setup.py
salure_helpers/monday/__init__.py
salure_helpers/monday/extract_monday.py
salure_helpers/monday/extract_tracket.py
salure_helpers/monday/upload_tracket.py
salure_helpers_monday.egg-info/PKG-INFO
salure_helpers_monday.egg-info/SOURCES.txt
salure_helpers_monday.egg-info/dependency_links.txt
salure_helpers_monday.egg-info/not-zip-safe
salure_helpers_monday.egg-info/requires.txt
salure_helpers_monday.egg-info/top_level.txt