Metadata-Version: 1.0
Name: salure-helpers-monday
Version: 0.7.5
Summary: Monday.com wrapper from Salure
Home-page: UNKNOWN
Author: D&A Salure
Author-email: support@salureconnnect.com
License: Salure License
Platform: UNKNOWN
